CHANGES
LICENSE
README
setup.py
mirpy/__init__.py
mirpy/commands.py
mirpy/wrapper.py
mirpy.egg-info/PKG-INFO
mirpy.egg-info/SOURCES.txt
mirpy.egg-info/dependency_links.txt
mirpy.egg-info/top_level.txt
mirpy.egg-info/zip-safe