Metadata-Version: 1.0
Name: mirpy
Version: 0.3.1
Summary: Pure-python miriad CLI wrapper.
Home-page: http://www.atnf.csiro.au
Author: Malte Marquarding
Author-email: Malte.Marquarding@csiro.au
License: GPL
Keywords: miriad,astronomy,radio astronomy
Platform: UNKNOWN
Classifier: Development Status :: 5 - Production/Stable
Classifier: Intended Audience :: Science/Research
Classifier: License :: OSI Approved :: GNU General Public License (GPL)
Classifier: Operating System :: Unix
Classifier: Programming Language :: Python
Classifier: Topic :: Scientific/Engineering :: Astronomy
Classifier: Topic :: Software Development :: Libraries :: Python Modules
